siobrultech_protocols/__init__.py
siobrultech_protocols/py.typed
siobrultech_protocols/gem/__init__.py
siobrultech_protocols/gem/api.py
siobrultech_protocols/gem/const.py
siobrultech_protocols/gem/fields.py
siobrultech_protocols/gem/packets.py
siobrultech_protocols/gem/protocol.py
tests/__init__.py
siobrultech_protocols-0.14.0.dist-info/LICENSE
siobrultech_protocols-0.14.0.dist-info/METADATA
siobrultech_protocols-0.14.0.dist-info/WHEEL
siobrultech_protocols-0.14.0.dist-info/top_level.txt
siobrultech_protocols-0.14.0.dist-info/RECORD
