Metadata-Version: 2.1
Name: siobrultech-protocols
Version: 0.14.0
Summary: A Sans-I/O Python client library for Brultech Devices
Author: Shawn Wilsher
Author-email: me@shawnwilsher.com
Project-URL: Bug Reports, https://github.com/sdwilsh/siobrultech-protocols/issues
Project-URL: Release Notes, https://github.com/sdwilsh/siobrultech-protocols/releases/
Project-URL: Source, https://github.com/sdwilsh/siobrultech-protocols
Classifier: Development Status :: 4 - Beta
Classifier: License :: OSI Approved :: MIT License
Classifier: Operating System :: OS Independent
Classifier: Programming Language :: Python :: 3.8
Classifier: Programming Language :: Python :: 3.9
Classifier: Programming Language :: Python :: 3.10
Classifier: Programming Language :: Python :: 3.11
Requires-Python: <4,>3.8
License-File: LICENSE
